setup.py
dcsmarket/__init__.py
dcsmarket/api.py
dcsmarket/basequotation.py
dcsmarket/dcsreal.py
dcsmarket/helpers.py
dcsmarket/kline.py
dcsmarket/minuteKline.py
dcsmarket/real.py
dcsmarket.egg-info/PKG-INFO
dcsmarket.egg-info/SOURCES.txt
dcsmarket.egg-info/dependency_links.txt
dcsmarket.egg-info/requires.txt
dcsmarket.egg-info/top_level.txt