Metadata-Version: 1.1
Name: dcsmarket
Version: 1.8.3.1
Summary: 大操手量化投资，股票行情数据接口
Home-page: https://dacaoshou.com
Author: 大操手量化投资
Author-email: yecaimeiv1@163.com
License: UNKNOWN
Keywords: stock,data,大操手
Platform: UNKNOWN
Classifier: Intended Audience :: Developers
Classifier: Operating System :: OS Independent
Classifier: Natural Language :: Chinese (Simplified)
Classifier: Programming Language :: Python
Classifier: Programming Language :: Python :: 3
Classifier: Programming Language :: Python :: 3.2
Classifier: Programming Language :: Python :: 3.3
Classifier: Programming Language :: Python :: 3.4
Classifier: Programming Language :: Python :: 3.5
Classifier: Programming Language :: Python :: 3.6
Classifier: Programming Language :: Python :: 3.7
Classifier: Programming Language :: Python :: 3.8
Classifier: Topic :: Utilities
